krl_types/__init__.py
krl_types/auth/__init__.py
krl_types/auth/enums.py
krl_types/auth/models.py
krl_types/billing/__init__.py
krl_types/billing/currency.py
krl_types/billing/enums.py
krl_types/billing/models.py
krl_types/connectors/__init__.py
krl_types/connectors/metadata.py
krl_types/connectors/operations.py
krl_types/models/__init__.py
krl_types/models/execution.py
krl_types/models/metadata.py
krl_types-0.2.1.dist-info/METADATA
krl_types-0.2.1.dist-info/WHEEL
krl_types-0.2.1.dist-info/RECORD
