Metadata-Version: 2.4
Name: krl-types
Version: 0.2.1
Summary: Shared type definitions for the KRL Analytics Platform
Project-URL: Documentation, https://docs.krlabs.dev/krl-types
Project-URL: Repository, https://github.com/KR-Labs/krl-types
Project-URL: Changelog, https://github.com/KR-Labs/krl-types/blob/main/CHANGELOG.md
Author-email: KR-Labs Engineering <engineering@krlabs.dev>
License: Apache-2.0
Keywords: analytics,billing,enums,krl,types
Classifier: Development Status :: 4 - Beta
Classifier: Intended Audience :: Developers
Classifier: License :: OSI Approved :: Apache Software License
Classifier: Operating System :: OS Independent
Classifier: Programming Language :: Python :: 3
Classifier: Programming Language :: Python :: 3.11
Classifier: Programming Language :: Python :: 3.12
Classifier: Programming Language :: Python :: 3.13
Classifier: Topic :: Software Development :: Libraries :: Python Modules
Classifier: Typing :: Typed
Requires-Python: >=3.9
Requires-Dist: pydantic>=2.0.0
Provides-Extra: dev
Requires-Dist: mypy>=1.8.0; extra == 'dev'
Requires-Dist: pytest-cov>=4.1.0; extra == 'dev'
Requires-Dist: pytest>=7.4.0; extra == 'dev'
Requires-Dist: ruff>=0.1.0; extra == 'dev'
